[
    {
        "id": 1,
        "image": "images/avocado-toast.jpg",
        "isClicked": false
    },
    {
        "id": 2,
        "image": "images/bacon.jpg",
        "isClicked": false
    },
    {
        "id": 3,
        "image": "images/cereal.jpg",
        "isClicked": false
    },
    {
        "id": 4,
        "image": "images/cinnamon-rolls.jpg",
        "isClicked": false
    },
    {
        "id": 5,
        "image": "images/eggs-bacon.jpg",
        "isClicked": false
    },
    {
        "id": 6,
        "image": "images/omelette.jpg",
        "isClicked": false
    },
    {
        "id": 7,
        "image": "images/overnight-oats.jpg",
        "isClicked": false
    },
    {
        "id": 8,
        "image": "images/pancakes.jpg",
        "isClicked": false
    },
    {
        "id": 9,
        "image": "images/quinoa.jpg",
        "isClicked": false
    },
    {
        "id": 10,
        "image": "images/sandwich.jpg",
        "isClicked": false
    },
    {
        "id": 11,
        "image": "images/tacos.jpg",
        "isClicked": false
    },
    {
        "id": 12,
        "image": "images/waffle.jpg",
        "isClicked": false
    }
]